{
  "updated": "2026-06-30",
  "source": "Yahoo Finance futures quotes via yfinance",
  "generatedAt": "2026-06-30T23:47:28Z",
  "commodities": [
    {
      "name": "Cocoa",
      "symbol": "CC=F",
      "category": "Agriculture",
      "unit": "USD/mt",
      "price": 5064.0,
      "day": 3.45,
      "week": 11.42,
      "month": 29.08,
      "ytd": -16.5,
      "year": -45.87,
      "previous": 4895.0,
      "date": "2026-06-30"
    },
    {
      "name": "Coffee",
      "symbol": "KC=F",
      "category": "Agriculture",
      "unit": "USd/lb",
      "price": 302.15,
      "day": 3.8,
      "week": 4.93,
      "month": 13.76,
      "ytd": -13.36,
      "year": -1.5,
      "previous": 291.1,
      "date": "2026-06-30"
    },
    {
      "name": "Corn",
      "symbol": "ZC=F",
      "category": "Agriculture",
      "unit": "USd/bu",
      "price": 436.5,
      "day": 8.58,
      "week": 6.53,
      "month": -2.29,
      "ytd": -0.85,
      "year": 4.55,
      "previous": 402.0,
      "date": "2026-06-30"
    },
    {
      "name": "Cotton",
      "symbol": "CT=F",
      "category": "Agriculture",
      "unit": "USd/lb",
      "price": 76.62,
      "day": 6.42,
      "week": 3.6,
      "month": 0.62,
      "ytd": 19.22,
      "year": 15.6,
      "previous": 72.0,
      "date": "2026-06-30"
    },
    {
      "name": "Oats",
      "symbol": "ZO=F",
      "category": "Agriculture",
      "unit": "USd/bu",
      "price": 332.75,
      "day": 28.1,
      "week": 10.18,
      "month": -7.25,
      "ytd": 10.0,
      "year": -13.63,
      "previous": 259.75,
      "date": "2026-06-30"
    },
    {
      "name": "Orange Juice",
      "symbol": "OJ=F",
      "category": "Agriculture",
      "unit": "USd/lb",
      "price": 163.8,
      "day": 15.56,
      "week": 9.86,
      "month": 2.86,
      "ytd": -20.18,
      "year": -24.74,
      "previous": 141.75,
      "date": "2026-06-30"
    },
    {
      "name": "Rough Rice",
      "symbol": "ZR=F",
      "category": "Agriculture",
      "unit": "USD/cwt",
      "price": 13.335,
      "day": 0.91,
      "week": 3.41,
      "month": 5.79,
      "ytd": 38.98,
      "year": 1.76,
      "previous": 13.215,
      "date": "2026-06-30"
    },
    {
      "name": "Soybean Meal",
      "symbol": "ZM=F",
      "category": "Agriculture",
      "unit": "USD/ton",
      "price": 303.2,
      "day": -0.49,
      "week": 0.1,
      "month": -8.07,
      "ytd": 2.95,
      "year": 11.84,
      "previous": 304.7,
      "date": "2026-06-30"
    },
    {
      "name": "Soybean Oil",
      "symbol": "ZL=F",
      "category": "Agriculture",
      "unit": "USd/lb",
      "price": 65.21,
      "day": -5.59,
      "week": -7.62,
      "month": -16.1,
      "ytd": 35.66,
      "year": 24.33,
      "previous": 69.07,
      "date": "2026-06-30"
    },
    {
      "name": "Soybeans",
      "symbol": "ZS=F",
      "category": "Agriculture",
      "unit": "USd/bu",
      "price": 1143.5,
      "day": 3.13,
      "week": 2.37,
      "month": -3.64,
      "ytd": 10.97,
      "year": 11.26,
      "previous": 1108.75,
      "date": "2026-06-30"
    },
    {
      "name": "Sugar",
      "symbol": "SB=F",
      "category": "Agriculture",
      "unit": "USd/lb",
      "price": 14.8,
      "day": 3.57,
      "week": 10.28,
      "month": 5.26,
      "ytd": -1.4,
      "year": -4.39,
      "previous": 14.29,
      "date": "2026-06-30"
    },
    {
      "name": "Wheat",
      "symbol": "ZW=F",
      "category": "Agriculture",
      "unit": "USd/bu",
      "price": 587.5,
      "day": 3.16,
      "week": 0.13,
      "month": -3.77,
      "ytd": 15.88,
      "year": 11.96,
      "previous": 569.5,
      "date": "2026-06-30"
    },
    {
      "name": "Brent Crude Oil",
      "symbol": "BZ=F",
      "category": "Energy",
      "unit": "USD/bbl",
      "price": 73.49,
      "day": 0.46,
      "week": -4.66,
      "month": -20.16,
      "ytd": 20.77,
      "year": 8.7,
      "previous": 73.15,
      "date": "2026-06-30"
    },
    {
      "name": "Crude Oil WTI",
      "symbol": "CL=F",
      "category": "Energy",
      "unit": "USD/bbl",
      "price": 70.11,
      "day": -0.9,
      "week": -4.23,
      "month": -19.75,
      "ytd": 22.1,
      "year": 7.68,
      "previous": 70.75,
      "date": "2026-06-30"
    },
    {
      "name": "Heating Oil",
      "symbol": "HO=F",
      "category": "Energy",
      "unit": "USD/gal",
      "price": 3.2315,
      "day": -3.01,
      "week": 2.44,
      "month": -8.65,
      "ytd": 52.39,
      "year": 37.76,
      "previous": 3.3317,
      "date": "2026-06-30"
    },
    {
      "name": "Natural Gas",
      "symbol": "NG=F",
      "category": "Energy",
      "unit": "USD/MMBtu",
      "price": 3.257,
      "day": 2.39,
      "week": 3.5,
      "month": -1.0,
      "ytd": -11.64,
      "year": -5.76,
      "previous": 3.181,
      "date": "2026-06-30"
    },
    {
      "name": "RBOB Gasoline",
      "symbol": "RB=F",
      "category": "Energy",
      "unit": "USD/gal",
      "price": 2.9093,
      "day": -4.97,
      "week": -1.68,
      "month": -6.95,
      "ytd": 70.59,
      "year": 39.88,
      "previous": 3.0614,
      "date": "2026-06-30"
    },
    {
      "name": "CRB Index",
      "symbol": "DBC",
      "category": "Indexes",
      "unit": "USD",
      "price": 26.66,
      "day": 0.38,
      "week": -1.7,
      "month": -9.57,
      "ytd": 19.23,
      "year": 22.29,
      "previous": 26.56,
      "date": "2026-06-30"
    },
    {
      "name": "Containerized Freight Index",
      "symbol": "BDRY",
      "category": "Indexes",
      "unit": "Points",
      "price": 11.87,
      "day": 2.06,
      "week": 0.85,
      "month": -8.27,
      "ytd": 35.35,
      "year": 112.57,
      "previous": 11.63,
      "date": "2026-06-30"
    },
    {
      "name": "EU Carbon Permits",
      "symbol": "KRBN",
      "category": "Indexes",
      "unit": "USD",
      "price": 33.16,
      "day": 0.15,
      "week": -0.39,
      "month": -1.31,
      "ytd": -6.33,
      "year": 9.91,
      "previous": 33.11,
      "date": "2026-06-30"
    },
    {
      "name": "GSCI",
      "symbol": "^SPGSCI",
      "category": "Indexes",
      "unit": "Index Points",
      "price": 619.4468,
      "day": 0.08,
      "week": -1.55,
      "month": -10.82,
      "ytd": 12.93,
      "year": 13.51,
      "previous": 618.97,
      "date": "2026-06-30"
    },
    {
      "name": "Nuclear Energy Index",
      "symbol": "URA",
      "category": "Indexes",
      "unit": "USD",
      "price": 43.7,
      "day": -0.52,
      "week": -4.12,
      "month": -13.91,
      "ytd": 2.27,
      "year": 14.79,
      "previous": 43.93,
      "date": "2026-06-30"
    },
    {
      "name": "SSE Commodity Index",
      "symbol": "000066.SS",
      "category": "Indexes",
      "unit": "Index Points",
      "price": 3828.821,
      "day": null,
      "week": null,
      "month": null,
      "ytd": 0.0,
      "year": null,
      "previous": null,
      "date": "2026-06-30"
    },
    {
      "name": "Solar Energy Index",
      "symbol": "TAN",
      "category": "Indexes",
      "unit": "USD",
      "price": 59.15,
      "day": 2.69,
      "week": 1.01,
      "month": -19.99,
      "ytd": 20.42,
      "year": 73.26,
      "previous": 57.6,
      "date": "2026-06-30"
    },
    {
      "name": "Wind Energy Index",
      "symbol": "FAN",
      "category": "Indexes",
      "unit": "USD",
      "price": 24.98,
      "day": 1.13,
      "week": 1.3,
      "month": -4.77,
      "ytd": 22.03,
      "year": 36.65,
      "previous": 24.7,
      "date": "2026-06-30"
    },
    {
      "name": "World Container Index",
      "symbol": "BOAT",
      "category": "Indexes",
      "unit": "USD",
      "price": 37.91,
      "day": -1.17,
      "week": -9.18,
      "month": -5.51,
      "ytd": 20.11,
      "year": 32.23,
      "previous": 38.36,
      "date": "2026-06-30"
    },
    {
      "name": "Feeder Cattle",
      "symbol": "GF=F",
      "category": "Livestock",
      "unit": "USd/lb",
      "price": 364.35,
      "day": -0.85,
      "week": -1.03,
      "month": 4.57,
      "ytd": 4.03,
      "year": 18.33,
      "previous": 367.475,
      "date": "2026-06-30"
    },
    {
      "name": "Lean Hogs",
      "symbol": "HE=F",
      "category": "Livestock",
      "unit": "USd/lb",
      "price": 98.15,
      "day": 4.61,
      "week": 4.17,
      "month": 2.4,
      "ytd": 15.33,
      "year": -13.33,
      "previous": 93.825,
      "date": "2026-06-30"
    },
    {
      "name": "Live Cattle",
      "symbol": "LE=F",
      "category": "Livestock",
      "unit": "USd/lb",
      "price": 242.25,
      "day": -5.89,
      "week": -5.06,
      "month": -2.42,
      "ytd": 4.42,
      "year": 7.79,
      "previous": 257.4,
      "date": "2026-06-30"
    },
    {
      "name": "Copper",
      "symbol": "HG=F",
      "category": "Metals",
      "unit": "USD/lb",
      "price": 6.251,
      "day": 2.52,
      "week": 1.79,
      "month": -1.71,
      "ytd": 11.03,
      "year": 24.27,
      "previous": 6.0975,
      "date": "2026-06-30"
    },
    {
      "name": "Gold",
      "symbol": "GC=F",
      "category": "Metals",
      "unit": "USD/oz",
      "price": 4022.7,
      "day": 0.01,
      "week": -2.6,
      "month": -11.79,
      "ytd": -7.0,
      "year": 22.11,
      "previous": 4022.3,
      "date": "2026-06-30"
    },
    {
      "name": "Palladium",
      "symbol": "PA=F",
      "category": "Metals",
      "unit": "USD/oz",
      "price": 1212.0,
      "day": 0.13,
      "week": -1.52,
      "month": -10.95,
      "ytd": -25.61,
      "year": 5.8,
      "previous": 1210.4,
      "date": "2026-06-30"
    },
    {
      "name": "Platinum",
      "symbol": "PL=F",
      "category": "Metals",
      "unit": "USD/oz",
      "price": 1560.5,
      "day": -0.89,
      "week": -6.04,
      "month": -18.82,
      "ytd": -23.3,
      "year": 16.98,
      "previous": 1574.5,
      "date": "2026-06-30"
    },
    {
      "name": "Silver",
      "symbol": "SI=F",
      "category": "Metals",
      "unit": "USD/oz",
      "price": 59.03,
      "day": 1.47,
      "week": -4.82,
      "month": -21.93,
      "ytd": -15.83,
      "year": 64.65,
      "previous": 58.175,
      "date": "2026-06-30"
    }
  ],
  "groups": {
    "Indexes": {
      "label": "Indexes",
      "stocks": [
        {
          "symbol": "DBC",
          "safeSymbol": "DBC",
          "name": "CRB Index",
          "sector": "Indexes",
          "unit": "USD",
          "price": 26.66,
          "d": 0.38,
          "w": -1.7,
          "m": -9.57,
          "y": 19.23,
          "year": 22.29,
          "rank": 1
        },
        {
          "symbol": "^SPGSCI",
          "safeSymbol": "^SPGSCI",
          "name": "GSCI",
          "sector": "Indexes",
          "unit": "Index Points",
          "price": 619.4468,
          "d": 0.08,
          "w": -1.55,
          "m": -10.82,
          "y": 12.93,
          "year": 13.51,
          "rank": 2
        },
        {
          "symbol": "000066.SS",
          "safeSymbol": "000066-SS",
          "name": "SSE Commodity Index",
          "sector": "Indexes",
          "unit": "Index Points",
          "price": 3828.821,
          "d": null,
          "w": null,
          "m": null,
          "y": 0.0,
          "year": null,
          "rank": 3
        },
        {
          "symbol": "BOAT",
          "safeSymbol": "BOAT",
          "name": "World Container Index",
          "sector": "Indexes",
          "unit": "USD",
          "price": 37.91,
          "d": -1.17,
          "w": -9.18,
          "m": -5.51,
          "y": 20.11,
          "year": 32.23,
          "rank": 4
        },
        {
          "symbol": "BDRY",
          "safeSymbol": "BDRY",
          "name": "Containerized Freight Index",
          "sector": "Indexes",
          "unit": "Points",
          "price": 11.87,
          "d": 2.06,
          "w": 0.85,
          "m": -8.27,
          "y": 35.35,
          "year": 112.57,
          "rank": 5
        },
        {
          "symbol": "KRBN",
          "safeSymbol": "KRBN",
          "name": "EU Carbon Permits",
          "sector": "Indexes",
          "unit": "USD",
          "price": 33.16,
          "d": 0.15,
          "w": -0.39,
          "m": -1.31,
          "y": -6.33,
          "year": 9.91,
          "rank": 6
        },
        {
          "symbol": "FAN",
          "safeSymbol": "FAN",
          "name": "Wind Energy Index",
          "sector": "Indexes",
          "unit": "USD",
          "price": 24.98,
          "d": 1.13,
          "w": 1.3,
          "m": -4.77,
          "y": 22.03,
          "year": 36.65,
          "rank": 7
        },
        {
          "symbol": "URA",
          "safeSymbol": "URA",
          "name": "Nuclear Energy Index",
          "sector": "Indexes",
          "unit": "USD",
          "price": 43.7,
          "d": -0.52,
          "w": -4.12,
          "m": -13.91,
          "y": 2.27,
          "year": 14.79,
          "rank": 8
        },
        {
          "symbol": "TAN",
          "safeSymbol": "TAN",
          "name": "Solar Energy Index",
          "sector": "Indexes",
          "unit": "USD",
          "price": 59.15,
          "d": 2.69,
          "w": 1.01,
          "m": -19.99,
          "y": 20.42,
          "year": 73.26,
          "rank": 9
        }
      ]
    },
    "Energy": {
      "label": "Energy",
      "stocks": [
        {
          "symbol": "CL=F",
          "safeSymbol": "CL-F",
          "name": "Crude Oil WTI",
          "sector": "Energy",
          "unit": "USD/bbl",
          "price": 70.11,
          "d": -0.9,
          "w": -4.23,
          "m": -19.75,
          "y": 22.1,
          "year": 7.68,
          "rank": 10
        },
        {
          "symbol": "BZ=F",
          "safeSymbol": "BZ-F",
          "name": "Brent Crude Oil",
          "sector": "Energy",
          "unit": "USD/bbl",
          "price": 73.49,
          "d": 0.46,
          "w": -4.66,
          "m": -20.16,
          "y": 20.77,
          "year": 8.7,
          "rank": 11
        },
        {
          "symbol": "NG=F",
          "safeSymbol": "NG-F",
          "name": "Natural Gas",
          "sector": "Energy",
          "unit": "USD/MMBtu",
          "price": 3.257,
          "d": 2.39,
          "w": 3.5,
          "m": -1.0,
          "y": -11.64,
          "year": -5.76,
          "rank": 12
        },
        {
          "symbol": "HO=F",
          "safeSymbol": "HO-F",
          "name": "Heating Oil",
          "sector": "Energy",
          "unit": "USD/gal",
          "price": 3.2315,
          "d": -3.01,
          "w": 2.44,
          "m": -8.65,
          "y": 52.39,
          "year": 37.76,
          "rank": 13
        },
        {
          "symbol": "RB=F",
          "safeSymbol": "RB-F",
          "name": "RBOB Gasoline",
          "sector": "Energy",
          "unit": "USD/gal",
          "price": 2.9093,
          "d": -4.97,
          "w": -1.68,
          "m": -6.95,
          "y": 70.59,
          "year": 39.88,
          "rank": 14
        }
      ]
    },
    "Metals": {
      "label": "Metals",
      "stocks": [
        {
          "symbol": "GC=F",
          "safeSymbol": "GC-F",
          "name": "Gold",
          "sector": "Metals",
          "unit": "USD/oz",
          "price": 4022.7,
          "d": 0.01,
          "w": -2.6,
          "m": -11.79,
          "y": -7.0,
          "year": 22.11,
          "rank": 15
        },
        {
          "symbol": "SI=F",
          "safeSymbol": "SI-F",
          "name": "Silver",
          "sector": "Metals",
          "unit": "USD/oz",
          "price": 59.03,
          "d": 1.47,
          "w": -4.82,
          "m": -21.93,
          "y": -15.83,
          "year": 64.65,
          "rank": 16
        },
        {
          "symbol": "HG=F",
          "safeSymbol": "HG-F",
          "name": "Copper",
          "sector": "Metals",
          "unit": "USD/lb",
          "price": 6.251,
          "d": 2.52,
          "w": 1.79,
          "m": -1.71,
          "y": 11.03,
          "year": 24.27,
          "rank": 17
        },
        {
          "symbol": "PL=F",
          "safeSymbol": "PL-F",
          "name": "Platinum",
          "sector": "Metals",
          "unit": "USD/oz",
          "price": 1560.5,
          "d": -0.89,
          "w": -6.04,
          "m": -18.82,
          "y": -23.3,
          "year": 16.98,
          "rank": 18
        },
        {
          "symbol": "PA=F",
          "safeSymbol": "PA-F",
          "name": "Palladium",
          "sector": "Metals",
          "unit": "USD/oz",
          "price": 1212.0,
          "d": 0.13,
          "w": -1.52,
          "m": -10.95,
          "y": -25.61,
          "year": 5.8,
          "rank": 19
        }
      ]
    },
    "Agriculture": {
      "label": "Agriculture",
      "stocks": [
        {
          "symbol": "ZC=F",
          "safeSymbol": "ZC-F",
          "name": "Corn",
          "sector": "Agriculture",
          "unit": "USd/bu",
          "price": 436.5,
          "d": 8.58,
          "w": 6.53,
          "m": -2.29,
          "y": -0.85,
          "year": 4.55,
          "rank": 20
        },
        {
          "symbol": "ZS=F",
          "safeSymbol": "ZS-F",
          "name": "Soybeans",
          "sector": "Agriculture",
          "unit": "USd/bu",
          "price": 1143.5,
          "d": 3.13,
          "w": 2.37,
          "m": -3.64,
          "y": 10.97,
          "year": 11.26,
          "rank": 21
        },
        {
          "symbol": "ZM=F",
          "safeSymbol": "ZM-F",
          "name": "Soybean Meal",
          "sector": "Agriculture",
          "unit": "USD/ton",
          "price": 303.2,
          "d": -0.49,
          "w": 0.1,
          "m": -8.07,
          "y": 2.95,
          "year": 11.84,
          "rank": 22
        },
        {
          "symbol": "ZL=F",
          "safeSymbol": "ZL-F",
          "name": "Soybean Oil",
          "sector": "Agriculture",
          "unit": "USd/lb",
          "price": 65.21,
          "d": -5.59,
          "w": -7.62,
          "m": -16.1,
          "y": 35.66,
          "year": 24.33,
          "rank": 23
        },
        {
          "symbol": "ZW=F",
          "safeSymbol": "ZW-F",
          "name": "Wheat",
          "sector": "Agriculture",
          "unit": "USd/bu",
          "price": 587.5,
          "d": 3.16,
          "w": 0.13,
          "m": -3.77,
          "y": 15.88,
          "year": 11.96,
          "rank": 24
        },
        {
          "symbol": "ZO=F",
          "safeSymbol": "ZO-F",
          "name": "Oats",
          "sector": "Agriculture",
          "unit": "USd/bu",
          "price": 332.75,
          "d": 28.1,
          "w": 10.18,
          "m": -7.25,
          "y": 10.0,
          "year": -13.63,
          "rank": 25
        },
        {
          "symbol": "ZR=F",
          "safeSymbol": "ZR-F",
          "name": "Rough Rice",
          "sector": "Agriculture",
          "unit": "USD/cwt",
          "price": 13.335,
          "d": 0.91,
          "w": 3.41,
          "m": 5.79,
          "y": 38.98,
          "year": 1.76,
          "rank": 26
        },
        {
          "symbol": "KC=F",
          "safeSymbol": "KC-F",
          "name": "Coffee",
          "sector": "Agriculture",
          "unit": "USd/lb",
          "price": 302.15,
          "d": 3.8,
          "w": 4.93,
          "m": 13.76,
          "y": -13.36,
          "year": -1.5,
          "rank": 27
        },
        {
          "symbol": "CC=F",
          "safeSymbol": "CC-F",
          "name": "Cocoa",
          "sector": "Agriculture",
          "unit": "USD/mt",
          "price": 5064.0,
          "d": 3.45,
          "w": 11.42,
          "m": 29.08,
          "y": -16.5,
          "year": -45.87,
          "rank": 28
        },
        {
          "symbol": "SB=F",
          "safeSymbol": "SB-F",
          "name": "Sugar",
          "sector": "Agriculture",
          "unit": "USd/lb",
          "price": 14.8,
          "d": 3.57,
          "w": 10.28,
          "m": 5.26,
          "y": -1.4,
          "year": -4.39,
          "rank": 29
        },
        {
          "symbol": "CT=F",
          "safeSymbol": "CT-F",
          "name": "Cotton",
          "sector": "Agriculture",
          "unit": "USd/lb",
          "price": 76.62,
          "d": 6.42,
          "w": 3.6,
          "m": 0.62,
          "y": 19.22,
          "year": 15.6,
          "rank": 30
        },
        {
          "symbol": "OJ=F",
          "safeSymbol": "OJ-F",
          "name": "Orange Juice",
          "sector": "Agriculture",
          "unit": "USd/lb",
          "price": 163.8,
          "d": 15.56,
          "w": 9.86,
          "m": 2.86,
          "y": -20.18,
          "year": -24.74,
          "rank": 31
        }
      ]
    },
    "Livestock": {
      "label": "Livestock",
      "stocks": [
        {
          "symbol": "LE=F",
          "safeSymbol": "LE-F",
          "name": "Live Cattle",
          "sector": "Livestock",
          "unit": "USd/lb",
          "price": 242.25,
          "d": -5.89,
          "w": -5.06,
          "m": -2.42,
          "y": 4.42,
          "year": 7.79,
          "rank": 32
        },
        {
          "symbol": "HE=F",
          "safeSymbol": "HE-F",
          "name": "Lean Hogs",
          "sector": "Livestock",
          "unit": "USd/lb",
          "price": 98.15,
          "d": 4.61,
          "w": 4.17,
          "m": 2.4,
          "y": 15.33,
          "year": -13.33,
          "rank": 33
        },
        {
          "symbol": "GF=F",
          "safeSymbol": "GF-F",
          "name": "Feeder Cattle",
          "sector": "Livestock",
          "unit": "USd/lb",
          "price": 364.35,
          "d": -0.85,
          "w": -1.03,
          "m": 4.57,
          "y": 4.03,
          "year": 18.33,
          "rank": 34
        }
      ]
    }
  },
  "stocks": [
    {
      "symbol": "DBC",
      "safeSymbol": "DBC",
      "name": "CRB Index",
      "sector": "Indexes",
      "unit": "USD",
      "price": 26.66,
      "d": 0.38,
      "w": -1.7,
      "m": -9.57,
      "y": 19.23,
      "year": 22.29,
      "rank": 1
    },
    {
      "symbol": "^SPGSCI",
      "safeSymbol": "^SPGSCI",
      "name": "GSCI",
      "sector": "Indexes",
      "unit": "Index Points",
      "price": 619.4468,
      "d": 0.08,
      "w": -1.55,
      "m": -10.82,
      "y": 12.93,
      "year": 13.51,
      "rank": 2
    },
    {
      "symbol": "000066.SS",
      "safeSymbol": "000066-SS",
      "name": "SSE Commodity Index",
      "sector": "Indexes",
      "unit": "Index Points",
      "price": 3828.821,
      "d": null,
      "w": null,
      "m": null,
      "y": 0.0,
      "year": null,
      "rank": 3
    },
    {
      "symbol": "BOAT",
      "safeSymbol": "BOAT",
      "name": "World Container Index",
      "sector": "Indexes",
      "unit": "USD",
      "price": 37.91,
      "d": -1.17,
      "w": -9.18,
      "m": -5.51,
      "y": 20.11,
      "year": 32.23,
      "rank": 4
    },
    {
      "symbol": "BDRY",
      "safeSymbol": "BDRY",
      "name": "Containerized Freight Index",
      "sector": "Indexes",
      "unit": "Points",
      "price": 11.87,
      "d": 2.06,
      "w": 0.85,
      "m": -8.27,
      "y": 35.35,
      "year": 112.57,
      "rank": 5
    },
    {
      "symbol": "KRBN",
      "safeSymbol": "KRBN",
      "name": "EU Carbon Permits",
      "sector": "Indexes",
      "unit": "USD",
      "price": 33.16,
      "d": 0.15,
      "w": -0.39,
      "m": -1.31,
      "y": -6.33,
      "year": 9.91,
      "rank": 6
    },
    {
      "symbol": "FAN",
      "safeSymbol": "FAN",
      "name": "Wind Energy Index",
      "sector": "Indexes",
      "unit": "USD",
      "price": 24.98,
      "d": 1.13,
      "w": 1.3,
      "m": -4.77,
      "y": 22.03,
      "year": 36.65,
      "rank": 7
    },
    {
      "symbol": "URA",
      "safeSymbol": "URA",
      "name": "Nuclear Energy Index",
      "sector": "Indexes",
      "unit": "USD",
      "price": 43.7,
      "d": -0.52,
      "w": -4.12,
      "m": -13.91,
      "y": 2.27,
      "year": 14.79,
      "rank": 8
    },
    {
      "symbol": "TAN",
      "safeSymbol": "TAN",
      "name": "Solar Energy Index",
      "sector": "Indexes",
      "unit": "USD",
      "price": 59.15,
      "d": 2.69,
      "w": 1.01,
      "m": -19.99,
      "y": 20.42,
      "year": 73.26,
      "rank": 9
    },
    {
      "symbol": "CL=F",
      "safeSymbol": "CL-F",
      "name": "Crude Oil WTI",
      "sector": "Energy",
      "unit": "USD/bbl",
      "price": 70.11,
      "d": -0.9,
      "w": -4.23,
      "m": -19.75,
      "y": 22.1,
      "year": 7.68,
      "rank": 10
    },
    {
      "symbol": "BZ=F",
      "safeSymbol": "BZ-F",
      "name": "Brent Crude Oil",
      "sector": "Energy",
      "unit": "USD/bbl",
      "price": 73.49,
      "d": 0.46,
      "w": -4.66,
      "m": -20.16,
      "y": 20.77,
      "year": 8.7,
      "rank": 11
    },
    {
      "symbol": "NG=F",
      "safeSymbol": "NG-F",
      "name": "Natural Gas",
      "sector": "Energy",
      "unit": "USD/MMBtu",
      "price": 3.257,
      "d": 2.39,
      "w": 3.5,
      "m": -1.0,
      "y": -11.64,
      "year": -5.76,
      "rank": 12
    },
    {
      "symbol": "HO=F",
      "safeSymbol": "HO-F",
      "name": "Heating Oil",
      "sector": "Energy",
      "unit": "USD/gal",
      "price": 3.2315,
      "d": -3.01,
      "w": 2.44,
      "m": -8.65,
      "y": 52.39,
      "year": 37.76,
      "rank": 13
    },
    {
      "symbol": "RB=F",
      "safeSymbol": "RB-F",
      "name": "RBOB Gasoline",
      "sector": "Energy",
      "unit": "USD/gal",
      "price": 2.9093,
      "d": -4.97,
      "w": -1.68,
      "m": -6.95,
      "y": 70.59,
      "year": 39.88,
      "rank": 14
    },
    {
      "symbol": "GC=F",
      "safeSymbol": "GC-F",
      "name": "Gold",
      "sector": "Metals",
      "unit": "USD/oz",
      "price": 4022.7,
      "d": 0.01,
      "w": -2.6,
      "m": -11.79,
      "y": -7.0,
      "year": 22.11,
      "rank": 15
    },
    {
      "symbol": "SI=F",
      "safeSymbol": "SI-F",
      "name": "Silver",
      "sector": "Metals",
      "unit": "USD/oz",
      "price": 59.03,
      "d": 1.47,
      "w": -4.82,
      "m": -21.93,
      "y": -15.83,
      "year": 64.65,
      "rank": 16
    },
    {
      "symbol": "HG=F",
      "safeSymbol": "HG-F",
      "name": "Copper",
      "sector": "Metals",
      "unit": "USD/lb",
      "price": 6.251,
      "d": 2.52,
      "w": 1.79,
      "m": -1.71,
      "y": 11.03,
      "year": 24.27,
      "rank": 17
    },
    {
      "symbol": "PL=F",
      "safeSymbol": "PL-F",
      "name": "Platinum",
      "sector": "Metals",
      "unit": "USD/oz",
      "price": 1560.5,
      "d": -0.89,
      "w": -6.04,
      "m": -18.82,
      "y": -23.3,
      "year": 16.98,
      "rank": 18
    },
    {
      "symbol": "PA=F",
      "safeSymbol": "PA-F",
      "name": "Palladium",
      "sector": "Metals",
      "unit": "USD/oz",
      "price": 1212.0,
      "d": 0.13,
      "w": -1.52,
      "m": -10.95,
      "y": -25.61,
      "year": 5.8,
      "rank": 19
    },
    {
      "symbol": "ZC=F",
      "safeSymbol": "ZC-F",
      "name": "Corn",
      "sector": "Agriculture",
      "unit": "USd/bu",
      "price": 436.5,
      "d": 8.58,
      "w": 6.53,
      "m": -2.29,
      "y": -0.85,
      "year": 4.55,
      "rank": 20
    },
    {
      "symbol": "ZS=F",
      "safeSymbol": "ZS-F",
      "name": "Soybeans",
      "sector": "Agriculture",
      "unit": "USd/bu",
      "price": 1143.5,
      "d": 3.13,
      "w": 2.37,
      "m": -3.64,
      "y": 10.97,
      "year": 11.26,
      "rank": 21
    },
    {
      "symbol": "ZM=F",
      "safeSymbol": "ZM-F",
      "name": "Soybean Meal",
      "sector": "Agriculture",
      "unit": "USD/ton",
      "price": 303.2,
      "d": -0.49,
      "w": 0.1,
      "m": -8.07,
      "y": 2.95,
      "year": 11.84,
      "rank": 22
    },
    {
      "symbol": "ZL=F",
      "safeSymbol": "ZL-F",
      "name": "Soybean Oil",
      "sector": "Agriculture",
      "unit": "USd/lb",
      "price": 65.21,
      "d": -5.59,
      "w": -7.62,
      "m": -16.1,
      "y": 35.66,
      "year": 24.33,
      "rank": 23
    },
    {
      "symbol": "ZW=F",
      "safeSymbol": "ZW-F",
      "name": "Wheat",
      "sector": "Agriculture",
      "unit": "USd/bu",
      "price": 587.5,
      "d": 3.16,
      "w": 0.13,
      "m": -3.77,
      "y": 15.88,
      "year": 11.96,
      "rank": 24
    },
    {
      "symbol": "ZO=F",
      "safeSymbol": "ZO-F",
      "name": "Oats",
      "sector": "Agriculture",
      "unit": "USd/bu",
      "price": 332.75,
      "d": 28.1,
      "w": 10.18,
      "m": -7.25,
      "y": 10.0,
      "year": -13.63,
      "rank": 25
    },
    {
      "symbol": "ZR=F",
      "safeSymbol": "ZR-F",
      "name": "Rough Rice",
      "sector": "Agriculture",
      "unit": "USD/cwt",
      "price": 13.335,
      "d": 0.91,
      "w": 3.41,
      "m": 5.79,
      "y": 38.98,
      "year": 1.76,
      "rank": 26
    },
    {
      "symbol": "KC=F",
      "safeSymbol": "KC-F",
      "name": "Coffee",
      "sector": "Agriculture",
      "unit": "USd/lb",
      "price": 302.15,
      "d": 3.8,
      "w": 4.93,
      "m": 13.76,
      "y": -13.36,
      "year": -1.5,
      "rank": 27
    },
    {
      "symbol": "CC=F",
      "safeSymbol": "CC-F",
      "name": "Cocoa",
      "sector": "Agriculture",
      "unit": "USD/mt",
      "price": 5064.0,
      "d": 3.45,
      "w": 11.42,
      "m": 29.08,
      "y": -16.5,
      "year": -45.87,
      "rank": 28
    },
    {
      "symbol": "SB=F",
      "safeSymbol": "SB-F",
      "name": "Sugar",
      "sector": "Agriculture",
      "unit": "USd/lb",
      "price": 14.8,
      "d": 3.57,
      "w": 10.28,
      "m": 5.26,
      "y": -1.4,
      "year": -4.39,
      "rank": 29
    },
    {
      "symbol": "CT=F",
      "safeSymbol": "CT-F",
      "name": "Cotton",
      "sector": "Agriculture",
      "unit": "USd/lb",
      "price": 76.62,
      "d": 6.42,
      "w": 3.6,
      "m": 0.62,
      "y": 19.22,
      "year": 15.6,
      "rank": 30
    },
    {
      "symbol": "OJ=F",
      "safeSymbol": "OJ-F",
      "name": "Orange Juice",
      "sector": "Agriculture",
      "unit": "USd/lb",
      "price": 163.8,
      "d": 15.56,
      "w": 9.86,
      "m": 2.86,
      "y": -20.18,
      "year": -24.74,
      "rank": 31
    },
    {
      "symbol": "LE=F",
      "safeSymbol": "LE-F",
      "name": "Live Cattle",
      "sector": "Livestock",
      "unit": "USd/lb",
      "price": 242.25,
      "d": -5.89,
      "w": -5.06,
      "m": -2.42,
      "y": 4.42,
      "year": 7.79,
      "rank": 32
    },
    {
      "symbol": "HE=F",
      "safeSymbol": "HE-F",
      "name": "Lean Hogs",
      "sector": "Livestock",
      "unit": "USd/lb",
      "price": 98.15,
      "d": 4.61,
      "w": 4.17,
      "m": 2.4,
      "y": 15.33,
      "year": -13.33,
      "rank": 33
    },
    {
      "symbol": "GF=F",
      "safeSymbol": "GF-F",
      "name": "Feeder Cattle",
      "sector": "Livestock",
      "unit": "USd/lb",
      "price": 364.35,
      "d": -0.85,
      "w": -1.03,
      "m": 4.57,
      "y": 4.03,
      "year": 18.33,
      "rank": 34
    }
  ]
}