{"symbol":"ELDN","name":"Eledon Pharmaceuticals Inc","sector":"科技","marketCap":"$272.47M","updated":"2026-06-11","prices":[{"time":"2024-06-12","open":2.98,"high":3.09,"low":2.95,"close":2.96,"volume":103600},{"time":"2024-06-13","open":3.04,"high":3.2,"low":2.91,"close":2.94,"volume":204100},{"time":"2024-06-14","open":2.94,"high":3.08,"low":2.935,"close":3.03,"volume":144800},{"time":"2024-06-17","open":3.05,"high":3.16,"low":2.78,"close":2.82,"volume":231300},{"time":"2024-06-18","open":2.84,"high":2.961,"low":2.6,"close":2.61,"volume":146100},{"time":"2024-06-20","open":2.67,"high":2.83,"low":2.61,"close":2.63,"volume":118200},{"time":"2024-06-21","open":2.68,"high":2.8,"low":2.555,"close":2.73,"volume":793400},{"time":"2024-06-24","open":2.64,"high":2.74,"low":2.61,"close":2.61,"volume":107400},{"time":"2024-06-25","open":2.59,"high":2.59,"low":2.35,"close":2.38,"volume":129800},{"time":"2024-06-26","open":2.34,"high":2.66,"low":2.34,"close":2.54,"volume":112900},{"time":"2024-06-27","open":2.51,"high":2.63,"low":2.43,"close":2.6,"volume":50200},{"time":"2024-06-28","open":2.63,"high":2.65,"low":2.45,"close":2.64,"volume":109800},{"time":"2024-07-01","open":2.65,"high":2.68,"low":2.41,"close":2.51,"volume":77800},{"time":"2024-07-02","open":2.5,"high":2.52,"low":2.41,"close":2.41,"volume":49100},{"time":"2024-07-03","open":2.45,"high":2.52,"low":2.405,"close":2.46,"volume":17700},{"time":"2024-07-05","open":2.47,"high":2.6,"low":2.38,"close":2.49,"volume":115400},{"time":"2024-07-08","open":2.53,"high":2.58,"low":2.3,"close":2.47,"volume":90900},{"time":"2024-07-09","open":2.5,"high":2.55,"low":2.43,"close":2.49,"volume":57400},{"time":"2024-07-10","open":2.48,"high":2.48,"low":2.4,"close":2.43,"volume":24200},{"time":"2024-07-11","open":2.39,"high":2.52,"low":2.39,"close":2.47,"volume":39900},{"time":"2024-07-12","open":2.5,"high":2.57,"low":2.43,"close":2.54,"volume":63700},{"time":"2024-07-15","open":2.51,"high":2.665,"low":2.47,"close":2.61,"volume":53800},{"time":"2024-07-16","open":2.68,"high":2.85,"low":2.67,"close":2.83,"volume":157300},{"time":"2024-07-17","open":2.78,"high":2.83,"low":2.7,"close":2.75,"volume":44500},{"time":"2024-07-18","open":2.72,"high":2.75,"low":2.64,"close":2.65,"volume":36600},{"time":"2024-07-19","open":2.65,"high":2.77,"low":2.65,"close":2.7,"volume":37400},{"time":"2024-07-22","open":2.73,"high":2.76,"low":2.38,"close":2.76,"volume":135600},{"time":"2024-07-23","open":2.89,"high":3.24,"low":2.725,"close":3.13,"volume":843300},{"time":"2024-07-24","open":3.3,"high":3.345,"low":3.05,"close":3.19,"volume":262100},{"time":"2024-07-25","open":3.23,"high":3.23,"low":2.87,"close":3.0,"volume":114200},{"time":"2024-07-26","open":3.03,"high":3.045,"low":2.8,"close":2.95,"volume":53600},{"time":"2024-07-29","open":2.97,"high":3.04,"low":2.81,"close":2.85,"volume":64400},{"time":"2024-07-30","open":2.85,"high":2.91,"low":2.7,"close":2.76,"volume":97200},{"time":"2024-07-31","open":2.79,"high":2.99,"low":2.79,"close":2.94,"volume":72600},{"time":"2024-08-01","open":2.93,"high":2.93,"low":2.82,"close":2.89,"volume":65300},{"time":"2024-08-02","open":2.8,"high":2.85,"low":2.7,"close":2.76,"volume":61400},{"time":"2024-08-05","open":2.6,"high":2.73,"low":2.55,"close":2.69,"volume":68500},{"time":"2024-08-06","open":2.68,"high":2.74,"low":2.53,"close":2.63,"volume":32600},{"time":"2024-08-07","open":2.66,"high":2.74,"low":2.57,"close":2.6,"volume":45400},{"time":"2024-08-08","open":2.57,"high":2.64,"low":2.57,"close":2.58,"volume":23900},{"time":"2024-08-09","open":2.57,"high":2.68,"low":2.57,"close":2.62,"volume":33400},{"time":"2024-08-12","open":2.53,"high":2.69,"low":2.53,"close":2.66,"volume":25700},{"time":"2024-08-13","open":2.7,"high":2.82,"low":2.6,"close":2.72,"volume":95600},{"time":"2024-08-14","open":2.73,"high":2.78,"low":2.6,"close":2.7,"volume":27900},{"time":"2024-08-15","open":2.61,"high":2.77,"low":2.57,"close":2.74,"volume":25600},{"time":"2024-08-16","open":2.72,"high":2.8,"low":2.66,"close":2.73,"volume":19700},{"time":"2024-08-19","open":2.72,"high":2.78,"low":2.59,"close":2.755,"volume":51000},{"time":"2024-08-20","open":2.82,"high":2.89,"low":2.7,"close":2.85,"volume":62700},{"time":"2024-08-21","open":2.83,"high":2.98,"low":2.76,"close":2.87,"volume":96300},{"time":"2024-08-22","open":2.92,"high":2.993,"low":2.85,"close":2.95,"volume":120100},{"time":"2024-08-23","open":3.0,"high":3.0,"low":2.83,"close":2.9,"volume":78300},{"time":"2024-08-26","open":2.94,"high":2.97,"low":2.82,"close":2.9,"volume":28700},{"time":"2024-08-27","open":2.88,"high":2.946,"low":2.84,"close":2.86,"volume":22000},{"time":"2024-08-28","open":2.86,"high":2.87,"low":2.71,"close":2.85,"volume":36600},{"time":"2024-08-29","open":2.85,"high":2.892,"low":2.77,"close":2.85,"volume":22500},{"time":"2024-08-30","open":2.89,"high":2.917,"low":2.72,"close":2.81,"volume":33000},{"time":"2024-09-03","open":2.78,"high":2.85,"low":2.655,"close":2.74,"volume":54000},{"time":"2024-09-04","open":2.67,"high":2.67,"low":2.54,"close":2.58,"volume":37700},{"time":"2024-09-05","open":2.61,"high":2.61,"low":2.43,"close":2.57,"volume":68100},{"time":"2024-09-06","open":2.6,"high":2.6,"low":2.42,"close":2.54,"volume":35900},{"time":"2024-09-09","open":2.44,"high":2.59,"low":2.42,"close":2.47,"volume":92000},{"time":"2024-09-10","open":2.48,"high":2.8,"low":2.479,"close":2.65,"volume":56800},{"time":"2024-09-11","open":2.55,"high":2.72,"low":2.46,"close":2.56,"volume":62600},{"time":"2024-09-12","open":2.54,"high":2.595,"low":2.49,"close":2.52,"volume":22400},{"time":"2024-09-13","open":2.5,"high":2.75,"low":2.5,"close":2.65,"volume":165900},{"time":"2024-09-16","open":2.62,"high":2.68,"low":2.55,"close":2.59,"volume":26800},{"time":"2024-09-17","open":2.56,"high":2.62,"low":2.5,"close":2.52,"volume":29400},{"time":"2024-09-18","open":2.54,"high":2.65,"low":2.5,"close":2.5,"volume":69400},{"time":"2024-09-19","open":2.55,"high":2.63,"low":2.48,"close":2.48,"volume":36700},{"time":"2024-09-20","open":2.51,"high":2.67,"low":2.48,"close":2.65,"volume":152400},{"time":"2024-09-23","open":2.61,"high":2.66,"low":2.55,"close":2.55,"volume":45800},{"time":"2024-09-24","open":2.61,"high":2.636,"low":2.47,"close":2.52,"volume":122600},{"time":"2024-09-25","open":2.53,"high":2.58,"low":2.45,"close":2.49,"volume":30800},{"time":"2024-09-26","open":2.61,"high":2.61,"low":2.45,"close":2.54,"volume":62800},{"time":"2024-09-27","open":2.51,"high":2.55,"low":2.45,"close":2.49,"volume":41500},{"time":"2024-09-30","open":2.49,"high":2.55,"low":2.375,"close":2.49,"volume":343900},{"time":"2024-10-01","open":2.45,"high":2.52,"low":2.41,"close":2.44,"volume":25600},{"time":"2024-10-02","open":2.44,"high":2.512,"low":2.38,"close":2.51,"volume":56600},{"time":"2024-10-03","open":2.5,"high":2.59,"low":2.44,"close":2.55,"volume":26600},{"time":"2024-10-04","open":2.52,"high":2.67,"low":2.52,"close":2.62,"volume":18400},{"time":"2024-10-07","open":2.64,"high":2.662,"low":2.561,"close":2.62,"volume":40100},{"time":"2024-10-08","open":2.62,"high":2.68,"low":2.581,"close":2.62,"volume":27300},{"time":"2024-10-09","open":2.63,"high":2.683,"low":2.598,"close":2.64,"volume":22600},{"time":"2024-10-10","open":2.69,"high":2.7,"low":2.56,"close":2.69,"volume":29800},{"time":"2024-10-11","open":2.65,"high":2.72,"low":2.6,"close":2.68,"volume":57400},{"time":"2024-10-14","open":2.65,"high":2.8,"low":2.65,"close":2.75,"volume":65700},{"time":"2024-10-15","open":2.78,"high":2.97,"low":2.75,"close":2.95,"volume":97600},{"time":"2024-10-16","open":2.98,"high":2.98,"low":2.76,"close":2.93,"volume":39300},{"time":"2024-10-17","open":2.92,"high":2.963,"low":2.8,"close":2.81,"volume":17400},{"time":"2024-10-18","open":2.86,"high":2.97,"low":2.76,"close":2.97,"volume":60500},{"time":"2024-10-21","open":2.9,"high":3.086,"low":2.9,"close":3.03,"volume":150700},{"time":"2024-10-22","open":3.03,"high":3.281,"low":2.95,"close":3.165,"volume":122600},{"time":"2024-10-23","open":3.25,"high":3.65,"low":3.16,"close":3.49,"volume":256700},{"time":"2024-10-24","open":3.54,"high":3.63,"low":3.4,"close":3.54,"volume":93300},{"time":"2024-10-25","open":3.57,"high":3.57,"low":3.25,"close":3.39,"volume":94800},{"time":"2024-10-28","open":3.46,"high":3.65,"low":3.2,"close":3.37,"volume":203000},{"time":"2024-10-29","open":3.78,"high":4.12,"low":3.54,"close":3.59,"volume":9920900},{"time":"2024-10-30","open":3.6,"high":4.41,"low":3.5,"close":4.19,"volume":3164700},{"time":"2024-10-31","open":4.07,"high":4.76,"low":3.95,"close":4.65,"volume":1003800},{"time":"2024-11-01","open":4.8,"high":5.54,"low":4.66,"close":5.3,"volume":1138400},{"time":"2024-11-04","open":5.35,"high":5.44,"low":4.59,"close":4.83,"volume":602300},{"time":"2024-11-05","open":4.82,"high":5.38,"low":4.758,"close":4.99,"volume":386900},{"time":"2024-11-06","open":5.1,"high":5.4,"low":5.01,"close":5.07,"volume":338700},{"time":"2024-11-07","open":5.07,"high":5.17,"low":4.89,"close":4.96,"volume":240400},{"time":"2024-11-08","open":5.0,"high":5.17,"low":4.74,"close":4.83,"volume":250700},{"time":"2024-11-11","open":4.93,"high":5.083,"low":4.8,"close":4.96,"volume":320200},{"time":"2024-11-12","open":4.91,"high":5.0,"low":4.69,"close":4.82,"volume":509900},{"time":"2024-11-13","open":4.71,"high":4.755,"low":4.15,"close":4.27,"volume":377700},{"time":"2024-11-14","open":4.22,"high":4.25,"low":3.99,"close":4.13,"volume":290900},{"time":"2024-11-15","open":4.13,"high":4.13,"low":3.91,"close":4.0,"volume":235000},{"time":"2024-11-18","open":3.92,"high":4.07,"low":3.76,"close":3.9,"volume":242000},{"time":"2024-11-19","open":3.82,"high":4.04,"low":3.8,"close":3.88,"volume":403300},{"time":"2024-11-20","open":3.9,"high":4.17,"low":3.76,"close":3.85,"volume":423700},{"time":"2024-11-21","open":3.84,"high":4.085,"low":3.81,"close":4.07,"volume":152200},{"time":"2024-11-22","open":4.08,"high":4.17,"low":3.93,"close":4.01,"volume":178700},{"time":"2024-11-25","open":4.06,"high":4.125,"low":3.95,"close":4.01,"volume":154700},{"time":"2024-11-26","open":3.97,"high":4.37,"low":3.95,"close":4.25,"volume":234800},{"time":"2024-11-27","open":4.3,"high":4.37,"low":4.16,"close":4.26,"volume":189500},{"time":"2024-11-29","open":4.31,"high":4.71,"low":4.14,"close":4.66,"volume":298200},{"time":"2024-12-02","open":4.73,"high":4.81,"low":4.34,"close":4.37,"volume":821900},{"time":"2024-12-03","open":4.39,"high":4.768,"low":4.24,"close":4.76,"volume":817700},{"time":"2024-12-04","open":4.76,"high":5.05,"low":4.57,"close":4.675,"volume":370400},{"time":"2024-12-05","open":4.68,"high":4.68,"low":4.34,"close":4.36,"volume":232200},{"time":"2024-12-06","open":4.47,"high":4.78,"low":4.14,"close":4.6,"volume":822400},{"time":"2024-12-09","open":4.77,"high":5.02,"low":4.62,"close":4.85,"volume":754600},{"time":"2024-12-10","open":4.95,"high":5.08,"low":4.79,"close":4.83,"volume":438800},{"time":"2024-12-11","open":4.78,"high":4.94,"low":4.59,"close":4.66,"volume":290100},{"time":"2024-12-12","open":4.54,"high":4.71,"low":4.38,"close":4.4,"volume":426800},{"time":"2024-12-13","open":4.37,"high":4.58,"low":4.32,"close":4.38,"volume":414400},{"time":"2024-12-16","open":4.39,"high":4.76,"low":4.39,"close":4.47,"volume":601000},{"time":"2024-12-17","open":4.42,"high":4.73,"low":4.35,"close":4.5,"volume":491100},{"time":"2024-12-18","open":4.5,"high":4.59,"low":4.09,"close":4.18,"volume":357300},{"time":"2024-12-19","open":4.22,"high":4.37,"low":4.06,"close":4.22,"volume":936900},{"time":"2024-12-20","open":4.2,"high":4.42,"low":3.95,"close":4.36,"volume":2231900},{"time":"2024-12-23","open":4.31,"high":4.36,"low":4.0,"close":4.19,"volume":441600},{"time":"2024-12-24","open":4.17,"high":4.31,"low":4.03,"close":4.27,"volume":262300},{"time":"2024-12-26","open":4.27,"high":4.38,"low":4.1,"close":4.37,"volume":563100},{"time":"2024-12-27","open":4.31,"high":4.4,"low":4.2,"close":4.35,"volume":514100},{"time":"2024-12-30","open":4.35,"high":4.35,"low":4.02,"close":4.14,"volume":760100},{"time":"2024-12-31","open":4.16,"high":4.2,"low":4.0,"close":4.12,"volume":377100},{"time":"2025-01-02","open":4.19,"high":4.67,"low":4.16,"close":4.29,"volume":540300},{"time":"2025-01-03","open":4.27,"high":4.98,"low":4.258,"close":4.83,"volume":659000},{"time":"2025-01-06","open":4.88,"high":4.88,"low":4.58,"close":4.64,"volume":280100},{"time":"2025-01-07","open":4.66,"high":4.66,"low":4.4,"close":4.51,"volume":208900},{"time":"2025-01-08","open":4.6,"high":4.66,"low":4.267,"close":4.3,"volume":258600},{"time":"2025-01-10","open":4.25,"high":4.25,"low":4.0,"close":4.04,"volume":234000},{"time":"2025-01-13","open":4.01,"high":4.045,"low":3.771,"close":3.89,"volume":391400},{"time":"2025-01-14","open":3.92,"high":4.0,"low":3.68,"close":3.71,"volume":368400},{"time":"2025-01-15","open":3.79,"high":4.07,"low":3.71,"close":4.05,"volume":990900},{"time":"2025-01-16","open":4.06,"high":4.19,"low":3.87,"close":4.03,"volume":232700},{"time":"2025-01-17","open":4.03,"high":4.04,"low":3.9,"close":4.02,"volume":151400},{"time":"2025-01-21","open":4.04,"high":4.11,"low":3.991,"close":4.09,"volume":150700},{"time":"2025-01-22","open":4.1,"high":4.28,"low":4.08,"close":4.21,"volume":227100},{"time":"2025-01-23","open":4.2,"high":4.275,"low":4.04,"close":4.25,"volume":127300},{"time":"2025-01-24","open":4.26,"high":4.48,"low":4.17,"close":4.43,"volume":230500},{"time":"2025-01-27","open":4.41,"high":4.67,"low":4.393,"close":4.66,"volume":452800},{"time":"2025-01-28","open":4.82,"high":4.85,"low":4.515,"close":4.745,"volume":399500},{"time":"2025-01-29","open":4.74,"high":4.78,"low":4.56,"close":4.74,"volume":300300},{"time":"2025-01-30","open":4.74,"high":4.86,"low":4.6,"close":4.78,"volume":247700},{"time":"2025-01-31","open":4.78,"high":4.82,"low":4.483,"close":4.52,"volume":282000},{"time":"2025-02-03","open":4.52,"high":4.64,"low":4.4,"close":4.46,"volume":173100},{"time":"2025-02-04","open":4.46,"high":4.68,"low":4.4,"close":4.67,"volume":229100},{"time":"2025-02-05","open":4.67,"high":4.83,"low":4.611,"close":4.71,"volume":150100},{"time":"2025-02-06","open":4.67,"high":4.85,"low":4.55,"close":4.75,"volume":209200},{"time":"2025-02-07","open":4.75,"high":4.965,"low":4.6,"close":4.7,"volume":375400},{"time":"2025-02-10","open":4.72,"high":4.768,"low":4.46,"close":4.52,"volume":255800},{"time":"2025-02-11","open":4.55,"high":4.677,"low":4.3,"close":4.33,"volume":221600},{"time":"2025-02-12","open":4.28,"high":4.54,"low":4.28,"close":4.5,"volume":202900},{"time":"2025-02-13","open":4.52,"high":4.55,"low":4.441,"close":4.49,"volume":123400},{"time":"2025-02-14","open":4.53,"high":4.575,"low":4.4,"close":4.53,"volume":112300},{"time":"2025-02-18","open":4.58,"high":4.625,"low":4.46,"close":4.59,"volume":194300},{"time":"2025-02-19","open":4.63,"high":4.65,"low":4.45,"close":4.51,"volume":189300},{"time":"2025-02-20","open":4.5,"high":4.5,"low":4.33,"close":4.34,"volume":157700},{"time":"2025-02-21","open":4.32,"high":4.391,"low":4.23,"close":4.29,"volume":147600},{"time":"2025-02-24","open":4.3,"high":4.47,"low":4.16,"close":4.16,"volume":151500},{"time":"2025-02-25","open":4.11,"high":4.19,"low":4.015,"close":4.14,"volume":197300},{"time":"2025-02-26","open":4.15,"high":4.315,"low":4.125,"close":4.26,"volume":164700},{"time":"2025-02-27","open":4.26,"high":4.44,"low":4.06,"close":4.08,"volume":176600},{"time":"2025-02-28","open":4.07,"high":4.21,"low":3.96,"close":4.15,"volume":142100},{"time":"2025-03-03","open":4.2,"high":4.285,"low":3.96,"close":4.005,"volume":395500},{"time":"2025-03-04","open":3.93,"high":3.98,"low":3.8,"close":3.89,"volume":301600},{"time":"2025-03-05","open":3.88,"high":4.02,"low":3.82,"close":3.94,"volume":146700},{"time":"2025-03-06","open":3.85,"high":4.01,"low":3.76,"close":3.81,"volume":145000},{"time":"2025-03-07","open":3.79,"high":3.97,"low":3.74,"close":3.79,"volume":350000},{"time":"2025-03-10","open":3.8,"high":3.8,"low":3.58,"close":3.59,"volume":407400},{"time":"2025-03-11","open":3.6,"high":3.75,"low":3.5,"close":3.69,"volume":207700},{"time":"2025-03-12","open":3.7,"high":3.82,"low":3.55,"close":3.75,"volume":256900},{"time":"2025-03-13","open":3.73,"high":3.751,"low":3.57,"close":3.6,"volume":176900},{"time":"2025-03-14","open":3.59,"high":3.695,"low":3.52,"close":3.65,"volume":111800},{"time":"2025-03-17","open":3.64,"high":3.71,"low":3.55,"close":3.63,"volume":196000},{"time":"2025-03-18","open":3.6,"high":3.66,"low":3.53,"close":3.54,"volume":173000},{"time":"2025-03-19","open":3.54,"high":3.625,"low":3.515,"close":3.56,"volume":127100},{"time":"2025-03-20","open":3.54,"high":3.63,"low":3.43,"close":3.44,"volume":627200},{"time":"2025-03-21","open":3.37,"high":3.55,"low":3.3,"close":3.51,"volume":310400},{"time":"2025-03-24","open":3.55,"high":3.66,"low":3.51,"close":3.61,"volume":309500},{"time":"2025-03-25","open":3.61,"high":3.66,"low":3.38,"close":3.47,"volume":254700},{"time":"2025-03-26","open":3.48,"high":3.48,"low":3.22,"close":3.37,"volume":292100},{"time":"2025-03-27","open":3.37,"high":3.43,"low":3.29,"close":3.41,"volume":266500},{"time":"2025-03-28","open":3.4,"high":3.443,"low":3.33,"close":3.35,"volume":179300},{"time":"2025-03-31","open":3.45,"high":3.45,"low":3.18,"close":3.39,"volume":425500},{"time":"2025-04-01","open":3.35,"high":3.38,"low":3.18,"close":3.22,"volume":347000},{"time":"2025-04-02","open":3.2,"high":3.4,"low":3.2,"close":3.31,"volume":185100},{"time":"2025-04-03","open":3.22,"high":3.22,"low":3.07,"close":3.16,"volume":198700},{"time":"2025-04-04","open":3.12,"high":3.13,"low":2.81,"close":2.83,"volume":413800},{"time":"2025-04-07","open":2.65,"high":2.84,"low":2.61,"close":2.83,"volume":361900},{"time":"2025-04-08","open":2.95,"high":3.101,"low":2.63,"close":2.71,"volume":306100},{"time":"2025-04-09","open":2.66,"high":2.98,"low":2.625,"close":2.97,"volume":221900},{"time":"2025-04-10","open":2.89,"high":2.985,"low":2.74,"close":2.83,"volume":150600},{"time":"2025-04-11","open":2.83,"high":2.96,"low":2.76,"close":2.94,"volume":160700},{"time":"2025-04-14","open":2.91,"high":3.05,"low":2.89,"close":2.98,"volume":154000},{"time":"2025-04-15","open":2.98,"high":3.209,"low":2.91,"close":3.01,"volume":145700},{"time":"2025-04-16","open":3.0,"high":3.045,"low":2.92,"close":3.0,"volume":152200},{"time":"2025-04-17","open":3.06,"high":3.12,"low":2.925,"close":2.99,"volume":143700},{"time":"2025-04-21","open":2.95,"high":3.13,"low":2.9,"close":2.98,"volume":107300},{"time":"2025-04-22","open":3.04,"high":3.4,"low":2.967,"close":3.38,"volume":377200},{"time":"2025-04-23","open":3.44,"high":3.56,"low":3.34,"close":3.36,"volume":240000},{"time":"2025-04-24","open":3.38,"high":3.41,"low":3.27,"close":3.36,"volume":131700},{"time":"2025-04-25","open":3.34,"high":3.35,"low":3.21,"close":3.24,"volume":89600},{"time":"2025-04-28","open":3.27,"high":3.37,"low":3.17,"close":3.28,"volume":104600},{"time":"2025-04-29","open":3.27,"high":3.435,"low":3.18,"close":3.27,"volume":61900},{"time":"2025-04-30","open":3.22,"high":3.28,"low":3.13,"close":3.16,"volume":103100},{"time":"2025-05-01","open":3.2,"high":3.44,"low":3.2,"close":3.28,"volume":114000},{"time":"2025-05-02","open":3.34,"high":3.47,"low":3.29,"close":3.31,"volume":96100},{"time":"2025-05-05","open":3.25,"high":3.51,"low":3.1,"close":3.1,"volume":108100},{"time":"2025-05-06","open":3.1,"high":3.1,"low":2.87,"close":2.87,"volume":189700},{"time":"2025-05-07","open":2.86,"high":3.03,"low":2.85,"close":3.0,"volume":266300},{"time":"2025-05-08","open":2.99,"high":3.37,"low":2.92,"close":3.17,"volume":198500},{"time":"2025-05-09","open":3.355,"high":3.41,"low":2.89,"close":2.89,"volume":328500},{"time":"2025-05-12","open":3.0,"high":3.09,"low":2.86,"close":2.87,"volume":191500},{"time":"2025-05-13","open":2.93,"high":3.11,"low":2.89,"close":2.9,"volume":300300},{"time":"2025-05-14","open":2.94,"high":3.16,"low":2.83,"close":2.83,"volume":240700},{"time":"2025-05-15","open":2.84,"high":3.038,"low":2.82,"close":2.89,"volume":176600},{"time":"2025-05-16","open":2.9,"high":2.97,"low":2.87,"close":2.87,"volume":136400},{"time":"2025-05-19","open":2.85,"high":3.12,"low":2.85,"close":3.04,"volume":278100},{"time":"2025-05-20","open":3.1,"high":3.11,"low":3.02,"close":3.06,"volume":178900},{"time":"2025-05-21","open":3.06,"high":3.15,"low":3.01,"close":3.15,"volume":186400},{"time":"2025-05-22","open":3.11,"high":3.18,"low":3.01,"close":3.02,"volume":186700},{"time":"2025-05-23","open":3.02,"high":3.11,"low":3.0,"close":3.05,"volume":175400},{"time":"2025-05-27","open":3.09,"high":3.27,"low":3.05,"close":3.15,"volume":406500},{"time":"2025-05-28","open":3.16,"high":3.25,"low":3.13,"close":3.15,"volume":135600},{"time":"2025-05-29","open":3.18,"high":3.24,"low":3.07,"close":3.09,"volume":217200},{"time":"2025-05-30","open":3.08,"high":3.08,"low":2.96,"close":3.0,"volume":184900},{"time":"2025-06-02","open":3.0,"high":3.14,"low":2.99,"close":3.06,"volume":244200},{"time":"2025-06-03","open":3.06,"high":3.18,"low":3.06,"close":3.17,"volume":132400},{"time":"2025-06-04","open":3.17,"high":3.265,"low":3.03,"close":3.03,"volume":301200},{"time":"2025-06-05","open":3.03,"high":3.03,"low":2.91,"close":2.98,"volume":190500},{"time":"2025-06-06","open":3.0,"high":3.175,"low":3.0,"close":3.08,"volume":198200},{"time":"2025-06-09","open":3.11,"high":3.13,"low":2.96,"close":2.99,"volume":137300},{"time":"2025-06-10","open":3.0,"high":3.07,"low":2.94,"close":2.99,"volume":205000},{"time":"2025-06-11","open":3.02,"high":3.08,"low":2.98,"close":3.0,"volume":170800},{"time":"2025-06-12","open":3.12,"high":3.12,"low":2.98,"close":3.0,"volume":120000},{"time":"2025-06-13","open":2.97,"high":3.045,"low":2.86,"close":2.87,"volume":195100},{"time":"2025-06-16","open":2.9,"high":3.033,"low":2.77,"close":2.8,"volume":246200},{"time":"2025-06-17","open":2.8,"high":2.875,"low":2.76,"close":2.81,"volume":214000},{"time":"2025-06-18","open":2.85,"high":2.9,"low":2.765,"close":2.78,"volume":199400},{"time":"2025-06-20","open":2.8,"high":2.899,"low":2.695,"close":2.72,"volume":244800},{"time":"2025-06-23","open":2.71,"high":2.755,"low":2.6,"close":2.6,"volume":645700},{"time":"2025-06-24","open":2.64,"high":2.79,"low":2.62,"close":2.75,"volume":269000},{"time":"2025-06-25","open":2.75,"high":2.84,"low":2.67,"close":2.74,"volume":299900},{"time":"2025-06-26","open":2.77,"high":2.912,"low":2.66,"close":2.75,"volume":333500},{"time":"2025-06-27","open":2.77,"high":2.79,"low":2.61,"close":2.69,"volume":7557700},{"time":"2025-06-30","open":2.7,"high":2.77,"low":2.6,"close":2.71,"volume":449600},{"time":"2025-07-01","open":2.68,"high":2.825,"low":2.64,"close":2.79,"volume":436700},{"time":"2025-07-02","open":2.78,"high":3.065,"low":2.75,"close":3.06,"volume":509800},{"time":"2025-07-03","open":3.08,"high":3.16,"low":3.06,"close":3.08,"volume":194700},{"time":"2025-07-07","open":3.07,"high":3.13,"low":3.0,"close":3.11,"volume":308600},{"time":"2025-07-08","open":3.16,"high":3.5,"low":3.16,"close":3.42,"volume":807200},{"time":"2025-07-09","open":3.46,"high":3.52,"low":3.33,"close":3.4,"volume":555000},{"time":"2025-07-10","open":3.39,"high":3.495,"low":3.301,"close":3.45,"volume":371800},{"time":"2025-07-11","open":3.43,"high":3.51,"low":3.357,"close":3.42,"volume":325300},{"time":"2025-07-14","open":3.55,"high":4.045,"low":3.55,"close":3.91,"volume":1672800},{"time":"2025-07-15","open":4.07,"high":4.085,"low":3.681,"close":3.85,"volume":686200},{"time":"2025-07-16","open":3.86,"high":3.889,"low":3.67,"close":3.78,"volume":519200},{"time":"2025-07-17","open":3.78,"high":3.85,"low":3.684,"close":3.75,"volume":457000},{"time":"2025-07-18","open":3.79,"high":3.83,"low":3.64,"close":3.7,"volume":376200},{"time":"2025-07-21","open":3.76,"high":3.93,"low":3.66,"close":3.69,"volume":596100},{"time":"2025-07-22","open":3.67,"high":3.78,"low":3.63,"close":3.71,"volume":504800},{"time":"2025-07-23","open":3.79,"high":3.85,"low":3.69,"close":3.81,"volume":349100},{"time":"2025-07-24","open":3.83,"high":3.95,"low":3.73,"close":3.73,"volume":595000},{"time":"2025-07-25","open":3.85,"high":3.85,"low":3.6,"close":3.62,"volume":540500},{"time":"2025-07-28","open":3.7,"high":3.82,"low":3.09,"close":3.23,"volume":1559400},{"time":"2025-07-29","open":3.2,"high":3.249,"low":2.9,"close":3.03,"volume":2192500},{"time":"2025-07-30","open":3.03,"high":3.27,"low":2.99,"close":3.16,"volume":409100},{"time":"2025-07-31","open":3.16,"high":3.265,"low":3.085,"close":3.15,"volume":681100},{"time":"2025-08-01","open":3.11,"high":3.43,"low":3.07,"close":3.38,"volume":653300},{"time":"2025-08-04","open":3.355,"high":3.47,"low":3.24,"close":3.25,"volume":1290000},{"time":"2025-08-05","open":3.28,"high":3.3,"low":3.12,"close":3.13,"volume":1112800},{"time":"2025-08-06","open":3.35,"high":3.51,"low":3.191,"close":3.44,"volume":1953500},{"time":"2025-08-07","open":2.8,"high":2.8,"low":2.41,"close":2.745,"volume":3628300},{"time":"2025-08-08","open":2.79,"high":2.815,"low":2.67,"close":2.715,"volume":786400},{"time":"2025-08-11","open":2.75,"high":2.77,"low":2.67,"close":2.71,"volume":1076500},{"time":"2025-08-12","open":2.68,"high":2.745,"low":2.635,"close":2.66,"volume":603800},{"time":"2025-08-13","open":2.66,"high":2.665,"low":2.56,"close":2.6,"volume":458100},{"time":"2025-08-14","open":2.54,"high":2.63,"low":2.54,"close":2.6,"volume":566700},{"time":"2025-08-15","open":2.63,"high":2.69,"low":2.544,"close":2.63,"volume":873000},{"time":"2025-08-18","open":2.64,"high":2.71,"low":2.555,"close":2.595,"volume":874500},{"time":"2025-08-19","open":2.57,"high":2.65,"low":2.51,"close":2.62,"volume":825800},{"time":"2025-08-20","open":2.6,"high":2.62,"low":2.51,"close":2.58,"volume":745800},{"time":"2025-08-21","open":2.57,"high":2.62,"low":2.55,"close":2.56,"volume":547300},{"time":"2025-08-22","open":2.55,"high":2.66,"low":2.55,"close":2.6,"volume":717200},{"time":"2025-08-25","open":2.64,"high":2.67,"low":2.53,"close":2.57,"volume":983500},{"time":"2025-08-26","open":2.58,"high":2.685,"low":2.559,"close":2.615,"volume":559000},{"time":"2025-08-27","open":2.62,"high":2.7,"low":2.56,"close":2.58,"volume":442000},{"time":"2025-08-28","open":2.58,"high":2.6,"low":2.54,"close":2.57,"volume":431000},{"time":"2025-08-29","open":2.59,"high":2.64,"low":2.535,"close":2.59,"volume":490700},{"time":"2025-09-02","open":2.59,"high":2.66,"low":2.55,"close":2.55,"volume":416200},{"time":"2025-09-03","open":2.56,"high":2.65,"low":2.54,"close":2.59,"volume":853700},{"time":"2025-09-04","open":2.59,"high":2.625,"low":2.54,"close":2.61,"volume":537800},{"time":"2025-09-05","open":2.61,"high":2.84,"low":2.61,"close":2.71,"volume":884600},{"time":"2025-09-08","open":2.71,"high":2.8,"low":2.57,"close":2.58,"volume":675800},{"time":"2025-09-09","open":2.59,"high":2.73,"low":2.59,"close":2.68,"volume":571300},{"time":"2025-09-10","open":2.71,"high":2.71,"low":2.58,"close":2.59,"volume":688300},{"time":"2025-09-11","open":2.58,"high":2.64,"low":2.53,"close":2.54,"volume":740900},{"time":"2025-09-12","open":2.52,"high":2.545,"low":2.41,"close":2.42,"volume":677500},{"time":"2025-09-15","open":2.43,"high":2.505,"low":2.42,"close":2.46,"volume":557100},{"time":"2025-09-16","open":2.56,"high":2.56,"low":2.315,"close":2.37,"volume":621500},{"time":"2025-09-17","open":2.38,"high":2.47,"low":2.35,"close":2.43,"volume":585800},{"time":"2025-09-18","open":2.48,"high":2.6,"low":2.45,"close":2.55,"volume":1515900},{"time":"2025-09-19","open":2.62,"high":2.64,"low":2.505,"close":2.55,"volume":1133000},{"time":"2025-09-22","open":2.56,"high":2.66,"low":2.52,"close":2.6,"volume":1098900},{"time":"2025-09-23","open":2.64,"high":2.71,"low":2.55,"close":2.55,"volume":1100800},{"time":"2025-09-24","open":2.55,"high":2.59,"low":2.41,"close":2.42,"volume":850200},{"time":"2025-09-25","open":2.46,"high":2.57,"low":2.45,"close":2.47,"volume":830500},{"time":"2025-09-26","open":2.5,"high":2.75,"low":2.44,"close":2.69,"volume":3644100},{"time":"2025-09-29","open":2.75,"high":2.79,"low":2.52,"close":2.54,"volume":1051800},{"time":"2025-09-30","open":2.54,"high":2.635,"low":2.48,"close":2.59,"volume":763000},{"time":"2025-10-01","open":2.57,"high":2.74,"low":2.57,"close":2.66,"volume":1068400},{"time":"2025-10-02","open":2.66,"high":2.77,"low":2.57,"close":2.76,"volume":1141900},{"time":"2025-10-03","open":2.8,"high":2.94,"low":2.8,"close":2.84,"volume":1013800},{"time":"2025-10-06","open":2.85,"high":2.94,"low":2.84,"close":2.86,"volume":817700},{"time":"2025-10-07","open":2.85,"high":2.9,"low":2.71,"close":2.73,"volume":760000},{"time":"2025-10-08","open":2.8,"high":2.879,"low":2.73,"close":2.87,"volume":1191200},{"time":"2025-10-09","open":2.86,"high":3.0,"low":2.86,"close":2.98,"volume":575100},{"time":"2025-10-10","open":2.98,"high":3.0,"low":2.73,"close":2.74,"volume":1253700},{"time":"2025-10-13","open":2.75,"high":2.81,"low":2.66,"close":2.72,"volume":673400},{"time":"2025-10-14","open":2.69,"high":2.749,"low":2.579,"close":2.71,"volume":599900},{"time":"2025-10-15","open":2.72,"high":2.8,"low":2.68,"close":2.74,"volume":2144200},{"time":"2025-10-16","open":2.8,"high":2.99,"low":2.745,"close":2.85,"volume":1324900},{"time":"2025-10-17","open":2.91,"high":3.7,"low":2.87,"close":3.44,"volume":5641200},{"time":"2025-10-20","open":3.5,"high":3.76,"low":3.25,"close":3.5,"volume":2434200},{"time":"2025-10-21","open":3.61,"high":3.61,"low":3.23,"close":3.49,"volume":1184600},{"time":"2025-10-22","open":3.46,"high":3.505,"low":3.26,"close":3.33,"volume":1932000},{"time":"2025-10-23","open":3.35,"high":3.39,"low":3.18,"close":3.29,"volume":1124800},{"time":"2025-10-24","open":3.32,"high":3.61,"low":3.27,"close":3.48,"volume":1581100},{"time":"2025-10-27","open":3.58,"high":3.9,"low":3.4,"close":3.83,"volume":2848100},{"time":"2025-10-28","open":3.82,"high":3.98,"low":3.67,"close":3.98,"volume":1493000},{"time":"2025-10-29","open":3.99,"high":4.49,"low":3.9,"close":4.25,"volume":3057200},{"time":"2025-10-30","open":4.25,"high":4.52,"low":4.2,"close":4.35,"volume":1926000},{"time":"2025-10-31","open":4.36,"high":4.45,"low":4.13,"close":4.32,"volume":1112100},{"time":"2025-11-03","open":4.37,"high":4.6,"low":4.13,"close":4.36,"volume":1134000},{"time":"2025-11-04","open":4.32,"high":4.32,"low":4.06,"close":4.16,"volume":1301300},{"time":"2025-11-05","open":4.17,"high":4.4,"low":3.99,"close":4.03,"volume":1741100},{"time":"2025-11-06","open":4.09,"high":4.25,"low":3.783,"close":4.1,"volume":4034600},{"time":"2025-11-07","open":2.0,"high":2.15,"low":1.43,"close":2.06,"volume":29781200},{"time":"2025-11-10","open":2.06,"high":2.4,"low":2.0,"close":2.25,"volume":3793000},{"time":"2025-11-11","open":2.2,"high":2.209,"low":2.021,"close":2.13,"volume":1411500},{"time":"2025-11-12","open":1.87,"high":1.93,"low":1.71,"close":1.89,"volume":5884600},{"time":"2025-11-13","open":1.9,"high":1.9,"low":1.6,"close":1.76,"volume":2815900},{"time":"2025-11-14","open":1.68,"high":1.83,"low":1.67,"close":1.76,"volume":2938100},{"time":"2025-11-17","open":1.8,"high":1.82,"low":1.6,"close":1.62,"volume":2984600},{"time":"2025-11-18","open":1.61,"high":1.65,"low":1.535,"close":1.54,"volume":7669800},{"time":"2025-11-19","open":1.54,"high":1.71,"low":1.385,"close":1.55,"volume":4581000},{"time":"2025-11-20","open":1.57,"high":1.64,"low":1.39,"close":1.39,"volume":2489600},{"time":"2025-11-21","open":1.4,"high":1.49,"low":1.35,"close":1.44,"volume":1546600},{"time":"2025-11-24","open":1.44,"high":1.635,"low":1.385,"close":1.61,"volume":2323900},{"time":"2025-11-25","open":1.61,"high":1.7,"low":1.585,"close":1.67,"volume":1570200},{"time":"2025-11-26","open":1.68,"high":1.685,"low":1.54,"close":1.55,"volume":1459500},{"time":"2025-11-28","open":1.58,"high":1.68,"low":1.57,"close":1.63,"volume":730500},{"time":"2025-12-01","open":1.6,"high":1.68,"low":1.53,"close":1.53,"volume":1013200},{"time":"2025-12-02","open":1.53,"high":1.609,"low":1.48,"close":1.48,"volume":934600},{"time":"2025-12-03","open":1.47,"high":1.61,"low":1.47,"close":1.59,"volume":927600},{"time":"2025-12-04","open":1.59,"high":1.67,"low":1.57,"close":1.59,"volume":1155600},{"time":"2025-12-05","open":1.61,"high":1.68,"low":1.58,"close":1.58,"volume":772400},{"time":"2025-12-08","open":1.62,"high":1.65,"low":1.58,"close":1.59,"volume":934600},{"time":"2025-12-09","open":1.6,"high":1.63,"low":1.56,"close":1.56,"volume":667500},{"time":"2025-12-10","open":1.56,"high":1.755,"low":1.56,"close":1.7,"volume":2022600},{"time":"2025-12-11","open":1.7,"high":1.74,"low":1.67,"close":1.7,"volume":808200},{"time":"2025-12-12","open":1.7,"high":1.73,"low":1.64,"close":1.64,"volume":895300},{"time":"2025-12-15","open":1.74,"high":1.75,"low":1.625,"close":1.64,"volume":794600},{"time":"2025-12-16","open":1.66,"high":1.7,"low":1.62,"close":1.63,"volume":1245300},{"time":"2025-12-17","open":1.65,"high":1.69,"low":1.56,"close":1.57,"volume":758300},{"time":"2025-12-18","open":1.59,"high":1.64,"low":1.55,"close":1.57,"volume":563900},{"time":"2025-12-19","open":1.6,"high":1.65,"low":1.585,"close":1.64,"volume":1573400},{"time":"2025-12-22","open":1.68,"high":1.69,"low":1.63,"close":1.64,"volume":731500},{"time":"2025-12-23","open":1.64,"high":1.64,"low":1.51,"close":1.52,"volume":1753400},{"time":"2025-12-24","open":1.53,"high":1.61,"low":1.52,"close":1.57,"volume":353500},{"time":"2025-12-26","open":1.56,"high":1.6,"low":1.53,"close":1.6,"volume":434800},{"time":"2025-12-29","open":1.59,"high":1.605,"low":1.54,"close":1.55,"volume":556900},{"time":"2025-12-30","open":1.55,"high":1.57,"low":1.5,"close":1.51,"volume":713600},{"time":"2025-12-31","open":1.51,"high":1.53,"low":1.44,"close":1.51,"volume":1277400},{"time":"2026-01-02","open":1.56,"high":1.62,"low":1.51,"close":1.62,"volume":680100},{"time":"2026-01-05","open":1.66,"high":1.67,"low":1.575,"close":1.65,"volume":1173900},{"time":"2026-01-06","open":1.65,"high":1.665,"low":1.63,"close":1.66,"volume":885400},{"time":"2026-01-07","open":1.66,"high":1.755,"low":1.66,"close":1.71,"volume":1024000},{"time":"2026-01-08","open":1.7,"high":1.75,"low":1.68,"close":1.73,"volume":592700},{"time":"2026-01-09","open":1.71,"high":1.75,"low":1.69,"close":1.73,"volume":690900},{"time":"2026-01-12","open":1.735,"high":1.92,"low":1.71,"close":1.91,"volume":1251500},{"time":"2026-01-13","open":1.91,"high":1.97,"low":1.7,"close":1.97,"volume":1023100},{"time":"2026-01-14","open":1.97,"high":2.05,"low":1.905,"close":2.03,"volume":785900},{"time":"2026-01-15","open":2.05,"high":2.1,"low":2.03,"close":2.07,"volume":614200},{"time":"2026-01-16","open":2.09,"high":2.175,"low":2.04,"close":2.12,"volume":1039600},{"time":"2026-01-20","open":2.09,"high":2.25,"low":2.09,"close":2.21,"volume":837800},{"time":"2026-01-21","open":2.2,"high":2.25,"low":2.1,"close":2.2,"volume":706200},{"time":"2026-01-22","open":2.22,"high":2.27,"low":2.195,"close":2.23,"volume":542800},{"time":"2026-01-23","open":2.25,"high":2.25,"low":2.1,"close":2.14,"volume":689700},{"time":"2026-01-26","open":2.15,"high":2.225,"low":2.09,"close":2.21,"volume":495200},{"time":"2026-01-27","open":2.2,"high":2.22,"low":2.161,"close":2.2,"volume":349000},{"time":"2026-01-28","open":2.2,"high":2.215,"low":2.1,"close":2.13,"volume":439800},{"time":"2026-01-29","open":2.13,"high":2.17,"low":2.06,"close":2.15,"volume":536400},{"time":"2026-01-30","open":2.14,"high":2.24,"low":2.12,"close":2.2,"volume":535100},{"time":"2026-02-02","open":2.22,"high":2.33,"low":2.16,"close":2.28,"volume":587500},{"time":"2026-02-03","open":2.29,"high":2.32,"low":2.11,"close":2.21,"volume":485700},{"time":"2026-02-04","open":2.22,"high":2.27,"low":2.13,"close":2.15,"volume":493400},{"time":"2026-02-05","open":2.14,"high":2.17,"low":1.955,"close":1.97,"volume":424300},{"time":"2026-02-06","open":1.98,"high":2.195,"low":1.98,"close":2.19,"volume":738100},{"time":"2026-02-09","open":2.19,"high":2.22,"low":2.08,"close":2.13,"volume":340000},{"time":"2026-02-10","open":2.14,"high":2.17,"low":2.06,"close":2.09,"volume":441800},{"time":"2026-02-11","open":2.1,"high":2.12,"low":1.98,"close":2.02,"volume":529200},{"time":"2026-02-12","open":2.02,"high":2.07,"low":1.98,"close":2.01,"volume":324200},{"time":"2026-02-13","open":2.02,"high":2.15,"low":2.0,"close":2.02,"volume":518900},{"time":"2026-02-17","open":2.17,"high":2.21,"low":2.09,"close":2.11,"volume":1033200},{"time":"2026-02-18","open":2.12,"high":2.195,"low":2.09,"close":2.1,"volume":481700},{"time":"2026-02-19","open":2.1,"high":2.23,"low":2.08,"close":2.22,"volume":548900},{"time":"2026-02-20","open":2.24,"high":2.25,"low":2.11,"close":2.19,"volume":1099200},{"time":"2026-02-23","open":2.16,"high":2.28,"low":2.145,"close":2.27,"volume":651900},{"time":"2026-02-24","open":2.28,"high":2.62,"low":2.268,"close":2.45,"volume":2113300},{"time":"2026-02-25","open":2.49,"high":2.59,"low":2.455,"close":2.47,"volume":777500},{"time":"2026-02-26","open":2.48,"high":2.53,"low":2.355,"close":2.42,"volume":656400},{"time":"2026-02-27","open":2.48,"high":2.65,"low":2.455,"close":2.62,"volume":1191200},{"time":"2026-03-02","open":2.58,"high":2.705,"low":2.52,"close":2.66,"volume":1261000},{"time":"2026-03-03","open":2.65,"high":2.65,"low":2.42,"close":2.5,"volume":897600},{"time":"2026-03-04","open":2.53,"high":2.61,"low":2.47,"close":2.51,"volume":611800},{"time":"2026-03-05","open":2.54,"high":2.72,"low":2.52,"close":2.62,"volume":1057200},{"time":"2026-03-06","open":2.6,"high":2.795,"low":2.52,"close":2.78,"volume":2145800},{"time":"2026-03-09","open":2.88,"high":3.105,"low":2.84,"close":2.9,"volume":2293800},{"time":"2026-03-10","open":3.0,"high":3.15,"low":2.87,"close":2.9,"volume":2017900},{"time":"2026-03-11","open":2.9,"high":2.97,"low":2.74,"close":2.76,"volume":1296900},{"time":"2026-03-12","open":2.78,"high":2.845,"low":2.66,"close":2.72,"volume":798200},{"time":"2026-03-13","open":2.76,"high":2.88,"low":2.655,"close":2.69,"volume":652500},{"time":"2026-03-16","open":2.76,"high":2.91,"low":2.655,"close":2.74,"volume":1208500},{"time":"2026-03-17","open":2.89,"high":2.94,"low":2.8,"close":2.88,"volume":2677200},{"time":"2026-03-18","open":3.0,"high":3.1,"low":2.9,"close":3.0,"volume":2107300},{"time":"2026-03-19","open":3.07,"high":3.07,"low":2.83,"close":2.85,"volume":1537400},{"time":"2026-03-20","open":2.87,"high":3.11,"low":2.86,"close":2.88,"volume":4028600},{"time":"2026-03-23","open":2.98,"high":3.19,"low":2.942,"close":3.1,"volume":2067300},{"time":"2026-03-24","open":3.11,"high":3.16,"low":2.84,"close":2.89,"volume":1372500},{"time":"2026-03-25","open":2.95,"high":2.97,"low":2.89,"close":2.92,"volume":933800},{"time":"2026-03-26","open":2.91,"high":3.02,"low":2.85,"close":2.96,"volume":966100},{"time":"2026-03-27","open":2.96,"high":3.03,"low":2.75,"close":2.83,"volume":864500},{"time":"2026-03-30","open":2.85,"high":2.896,"low":2.68,"close":2.71,"volume":1032600},{"time":"2026-03-31","open":2.76,"high":3.09,"low":2.73,"close":3.08,"volume":1912100},{"time":"2026-04-01","open":3.07,"high":3.167,"low":2.98,"close":3.0,"volume":1038500},{"time":"2026-04-02","open":3.0,"high":3.145,"low":2.9,"close":3.07,"volume":1187800},{"time":"2026-04-06","open":3.14,"high":3.28,"low":3.08,"close":3.09,"volume":1365600},{"time":"2026-04-07","open":3.09,"high":3.116,"low":2.97,"close":3.05,"volume":1196800},{"time":"2026-04-08","open":3.16,"high":3.2,"low":3.06,"close":3.13,"volume":1358500},{"time":"2026-04-09","open":3.09,"high":3.21,"low":3.08,"close":3.1,"volume":991700},{"time":"2026-04-10","open":3.1,"high":3.18,"low":3.065,"close":3.1,"volume":970800},{"time":"2026-04-13","open":3.12,"high":3.24,"low":3.1,"close":3.22,"volume":1602500},{"time":"2026-04-14","open":3.255,"high":3.31,"low":3.14,"close":3.2,"volume":906900},{"time":"2026-04-15","open":3.23,"high":3.44,"low":3.195,"close":3.3,"volume":2139000},{"time":"2026-04-16","open":3.4,"high":3.74,"low":3.275,"close":3.73,"volume":3045800},{"time":"2026-04-17","open":3.83,"high":4.15,"low":3.825,"close":3.98,"volume":4471400},{"time":"2026-04-20","open":4.089,"high":4.2,"low":3.905,"close":4.14,"volume":2308200},{"time":"2026-04-21","open":4.2,"high":4.2,"low":3.95,"close":3.96,"volume":2144100},{"time":"2026-04-22","open":4.0,"high":4.175,"low":3.87,"close":3.99,"volume":1660900},{"time":"2026-04-23","open":4.0,"high":4.05,"low":3.55,"close":3.59,"volume":2695900},{"time":"2026-04-24","open":3.61,"high":3.61,"low":3.4,"close":3.465,"volume":1678100},{"time":"2026-04-27","open":3.464,"high":3.65,"low":3.35,"close":3.46,"volume":1556400},{"time":"2026-04-28","open":3.45,"high":3.625,"low":3.4,"close":3.48,"volume":1064500},{"time":"2026-04-29","open":3.45,"high":3.56,"low":3.28,"close":3.34,"volume":1185800},{"time":"2026-04-30","open":3.37,"high":3.64,"low":3.36,"close":3.64,"volume":1303000},{"time":"2026-05-01","open":3.66,"high":3.75,"low":3.57,"close":3.69,"volume":1219000},{"time":"2026-05-04","open":3.67,"high":3.88,"low":3.65,"close":3.78,"volume":1006100},{"time":"2026-05-05","open":3.82,"high":3.86,"low":3.73,"close":3.78,"volume":729900},{"time":"2026-05-06","open":3.79,"high":3.89,"low":3.705,"close":3.8,"volume":1961100},{"time":"2026-05-07","open":3.8,"high":3.925,"low":3.67,"close":3.86,"volume":1332100},{"time":"2026-05-08","open":3.87,"high":3.995,"low":3.84,"close":3.88,"volume":1112100},{"time":"2026-05-11","open":3.88,"high":4.0,"low":3.79,"close":3.82,"volume":896900},{"time":"2026-05-12","open":3.81,"high":3.975,"low":3.79,"close":3.9,"volume":1330000},{"time":"2026-05-13","open":3.86,"high":3.945,"low":3.835,"close":3.88,"volume":1419600},{"time":"2026-05-14","open":3.92,"high":4.14,"low":3.84,"close":3.95,"volume":2040200},{"time":"2026-05-15","open":3.9,"high":3.93,"low":3.725,"close":3.8,"volume":992400},{"time":"2026-05-18","open":3.8,"high":3.86,"low":3.515,"close":3.58,"volume":1118300},{"time":"2026-05-19","open":3.54,"high":3.66,"low":3.41,"close":3.58,"volume":873200},{"time":"2026-05-20","open":3.55,"high":3.88,"low":3.55,"close":3.84,"volume":917700},{"time":"2026-05-21","open":3.79,"high":3.95,"low":3.79,"close":3.89,"volume":928300},{"time":"2026-05-22","open":3.92,"high":4.0,"low":3.82,"close":3.89,"volume":666500},{"time":"2026-05-26","open":3.94,"high":4.04,"low":3.88,"close":3.89,"volume":1419100},{"time":"2026-05-27","open":3.86,"high":3.97,"low":3.82,"close":3.9,"volume":963500},{"time":"2026-05-28","open":3.88,"high":3.885,"low":3.77,"close":3.87,"volume":681600},{"time":"2026-05-29","open":3.88,"high":3.9,"low":3.775,"close":3.81,"volume":794600},{"time":"2026-06-01","open":3.79,"high":3.81,"low":3.61,"close":3.76,"volume":900200},{"time":"2026-06-02","open":3.73,"high":3.73,"low":3.53,"close":3.53,"volume":950700},{"time":"2026-06-03","open":3.5,"high":3.51,"low":3.43,"close":3.49,"volume":1063000},{"time":"2026-06-04","open":3.5,"high":3.71,"low":3.49,"close":3.6,"volume":617000},{"time":"2026-06-05","open":3.59,"high":3.6,"low":3.38,"close":3.41,"volume":757800},{"time":"2026-06-08","open":3.745,"high":3.8,"low":3.4,"close":3.58,"volume":1829500},{"time":"2026-06-09","open":3.62,"high":3.715,"low":3.43,"close":3.55,"volume":1217500},{"time":"2026-06-10","open":3.56,"high":3.63,"low":3.45,"close":3.46,"volume":754200},{"time":"2026-06-11","open":3.46,"high":3.59,"low":3.38,"close":3.57,"volume":767700}]}